common.py
main.py
mongo_tool/delete.py
mongo_tool/insert.py
mongo_tool/query.py
mongo_tool/update.py
czh_mongo_py-0.0.1.0.dist-info/METADATA
czh_mongo_py-0.0.1.0.dist-info/WHEEL
czh_mongo_py-0.0.1.0.dist-info/entry_points.txt
czh_mongo_py-0.0.1.0.dist-info/RECORD
