Metadata-Version: 2.1
Name: czh-mongo-py
Version: 0.0.1.0
Summary: 
Author: xiangyouzhuan
Author-email: xiangyouzhuan2018@gmail.com
Requires-Python: >=3.8.5,<4.0.0
Classifier: Programming Language :: Python :: 3
Classifier: Programming Language :: Python :: 3.9
Classifier: Programming Language :: Python :: 3.10
Classifier: Programming Language :: Python :: 3.11
Requires-Dist: happy-python (>=0.4.7,<0.5.0)
Requires-Dist: pytest (>=7.4.1)
